{"steps": [[{"x": 375, "etape": 0, "index": 0, "precedents": [], "suivants": [[1, 0], [1, 1], [1, 2]]}], [{"x": 175, "etape": 1, "index": 0, "precedents": [], "suivants": [[2, 0]]}, {"x": 375, "etape": 1, "index": 1, "precedents": [], "suivants": [[4, 0], [3, 0], [3, 1]]}, {"x": 575, "etape": 1, "index": 2, "precedents": [], "suivants": [[3, 1]]}], [{"x": 175, "etape": 2, "index": 0, "precedents": [], "suivants": [[3, 0]]}], [{"x": 175, "etape": 3, "index": 0, "precedents": [], "suivants": [[4, 0]]}, {"x": 575, "etape": 3, "index": 1, "precedents": [], "suivants": [[4, 0]]}], [{"x": 375, "etape": 4, "index": 0, "precedents": [], "suivants": []}]]}